yamltable/__init__.py
yamltable/__main__.py
yamltable/py.typed
yamltable/typing.py
yamltable-0.1.5.dist-info/entry_points.txt
yamltable-0.1.5.dist-info/LICENSE.md
yamltable-0.1.5.dist-info/WHEEL
yamltable-0.1.5.dist-info/METADATA
yamltable-0.1.5.dist-info/RECORD
