Metadata-Version: 2.1
Name: yamltable
Version: 0.1.5
Summary: Command line utility for list organized YAML files.
Home-page: https://github.com/wolfgangwazzlestrauss/yamltable
License: MIT
Keywords: yaml
Author: Macklan Weinstein
Author-email: wolfgangwazzlestrauss@gmail.com
Requires-Python: >=3.6.1,<4.0.0
Classifier: License :: OSI Approved :: MIT License
Classifier: Programming Language :: Python :: 3
Classifier: Programming Language :: Python :: 3.7
Classifier: Programming Language :: Python :: 3.8
Requires-Dist: jsonschema (>=3.2.0,<4.0.0)
Requires-Dist: pyrsistent (>=0.14.11,<0.15.0)
Requires-Dist: pyyaml (>=5.2,<6.0)
Requires-Dist: typer (>=0.2.1,<0.3.0)
